announcementlink/__init__.py
announcementlink/main.py
announcementlink-1.1.dist-info/LICENSE.txt
announcementlink-1.1.dist-info/METADATA
announcementlink-1.1.dist-info/WHEEL
announcementlink-1.1.dist-info/top_level.txt
announcementlink-1.1.dist-info/RECORD
