Metadata-Version: 2.1
Name: announcementlink
Version: 1.1
Summary: A speech system for places like train stations that takes individual spoken words/phrases and connect them to create a sentence.
Home-page: https://github.com/Chookman5/AnnouncementLink
Author: Riley Brown
License: UNKNOWN
Platform: UNKNOWN
Classifier: Programming Language :: Python :: 3
Classifier: License :: OSI Approved :: GNU General Public License v3 (GPLv3)
Classifier: Operating System :: OS Independent
Requires-Python: >=3.6
